[
    {
        "id": "202309072318961473",
        "title": "自由竞争资本主义向垄断资本主义过渡的根源在于",
        "option": [
            "资本积累的一般规律；",
            "资本有机构成不断提高；",
            "资本主义的基本矛盾；",
            "竞争的结果"
        ],
        "answer": "C",
        "analysis": ""
    },
    {
        "id": "202309072318544968",
        "title": "资本主义经济发展中，资本集中的直接后果是",
        "option": [
            "社会总资本急剧增加；",
            "社会就业率明显提高；",
            "个别资本规模迅速扩大；",
            "绝对剩余价值总量快速增长"
        ],
        "answer": "C",
        "analysis": ""
    },
    {
        "id": "202309072318218921",
        "title": "垄断的形成是",
        "option": [
            "生产集中发展到一定阶段的结果；",
            "生产输出的结果；",
            "金融资本统治的结果；",
            "国家干预经济生活的结果"
        ],
        "answer": "A",
        "analysis": ""
    },
    {
        "id": "202309072318853455",
        "title": "主要资本主义国家相继由自由竞争阶段发展到垄断阶段的时期是",
        "option": [
            "18世纪末期；",
            "19世纪中期；",
            "19世纪末20世纪初；",
            "第二次世界大战后"
        ],
        "answer": "C",
        "analysis": ""
    },
    {
        "id": "202309072318183355",
        "title": "垄断利润是",
        "option": [
            "资本家获得的超额利润；",
            "垄断组织获得的平均利润；",
            "垄断组织获得的一般利润；",
            "垄断组织获得的超过平均利润的高额利润"
        ],
        "answer": "D",
        "analysis": ""
    },
    {
        "id": "202309072318918405",
        "title": "垄断价格形成的基础是",
        "option": [
            "垄断统治；",
            "垄断利润；",
            "自由竞争；",
            "资本主义私有制"
        ],
        "answer": "A",
        "analysis": ""
    },
    {
        "id": "20230907231884174",
        "title": "垄断价格的形成和垄断利润的产生表明",
        "option": [
            "价值规律不再起作用了；",
            "价值规律的作用受到了限制；",
            "价值规律的作用形式发生了变化；",
            "价值规律的内容发生了变化"
        ],
        "answer": "C",
        "analysis": ""
    },
    {
        "id": "202309072318397996",
        "title": "垄断资本主义国家全部经济生活的基础是",
        "option": [
            "垄断统治；",
            "资本输出；",
            "国际垄断同盟；",
            "占领殖民地"
        ],
        "answer": "A",
        "analysis": ""
    },
    {
        "id": "202309072318448221",
        "title": "各种垄断组织虽然形式不同，但本质都是为了",
        "option": [
            "避免两败俱伤；",
            "联合起来共同发展；",
            "相互之间竞争；",
            "获取高额垄断利润"
        ],
        "answer": "D",
        "analysis": ""
    },
    {
        "id": "202309072318778490",
        "title": "把一些法律上和生产上还是独立的大垄断企业在流通环节上统一起来进行垄断经营的垄断组织形式是",
        "option": [
            "卡特尔；",
            "辛迪加；",
            "托拉斯；",
            "康采恩"
        ],
        "answer": "A",
        "analysis": ""
    },
    {
        "id": "202309072318872334",
        "title": "垄断资本主义国家事实上的主宰者是",
        "option": [
            "银行资本家；",
            "工业资本家；",
            "金融寡头；",
            "商业资本家"
        ],
        "answer": "C",
        "analysis": ""
    },
    {
        "id": "202309072318366033",
        "title": "垄断资本主义时期占垄断地位的资本是",
        "option": [
            "产业资本；",
            "金融资本；",
            "银行资本；",
            "商业资本"
        ],
        "answer": "B",
        "analysis": ""
    },
    {
        "id": "202309072318497968",
        "title": "垄断资本在经济政治上统治的目的归根到底是为了",
        "option": [
            "规定垄断价格；",
            "获取高额垄断利润；",
            "掌握国家政权；",
            "避免两败俱伤"
        ],
        "answer": "B",
        "analysis": ""
    },
    {
        "id": "202309072318903846",
        "title": "垄断价格形成后，价值规律改变了",
        "option": [
            "内容变化；",
            "作用性质；",
            "作用形式；",
            "作用力度"
        ],
        "answer": "C",
        "analysis": ""
    },
    {
        "id": "202309072318164689",
        "title": "金融寡头在经济上的统治主要是通过__实现的",
        "option": [
            "参与制；",
            "个人联合；",
            "建立政策研究咨询机构对政府施加影响；",
            "掌握舆论工具控制新闻媒介"
        ],
        "answer": "A",
        "analysis": ""
    },
    {
        "id": "202309072318831818",
        "title": "金融寡头政治上的统治主要是通过__实现的",
        "option": [
            "合作参与制；",
            "个人联合；",
            "建立政策研究咨询机构对政府施加影响；",
            "掌握舆论工具控制新闻媒介"
        ],
        "answer": "B",
        "analysis": ""
    },
    {
        "id": "20230907231890688",
        "title": "为了获得高额垄断利润，垄断组织在采购原材料时多采取 ",
        "option": [
            "垄断高价；",
            "垄断低价；",
            "自由价格；",
            "市场价格"
        ],
        "answer": "B",
        "analysis": ""
    },
    {
        "id": "20230907231874632",
        "title": "垄断资本条件下垄断企业竞争的目的是为了",
        "option": [
            "获得平均利润；",
            "获得超额利润；",
            "获得高额垄断利润；",
            "消灭中小企业"
        ],
        "answer": "C",
        "analysis": ""
    },
    {
        "id": "202309072318352952",
        "title": "国家垄断资本主义是",
        "option": [
            "国家政权与垄断资本相结合的垄断资本主义；",
            "国家政权与垄断资本相分离的垄断资本主义；",
            "消除了生产无政府状态的垄断资本主义；",
            "解决了资本主义基本矛盾的垄断资本主义"
        ],
        "answer": "A",
        "analysis": ""
    },
    {
        "id": "202309072318626583",
        "title": "国家垄断资本主义的根本特征是",
        "option": [
            "国有企业的存在；",
            "国私共有的垄断资本；",
            "私人垄断资本的主导地位；",
            "国家对经济的干预和调节"
        ],
        "answer": "D",
        "analysis": ""
    },
    {
        "id": "202309072318848111",
        "title": "国家垄断资本主义的产生和发展表明",
        "option": [
            "资本主义仍然具有强大的生产力；",
            "社会主义制度很快就要建立；",
            "私有制已经被公有制所代替；",
            "为向社会主义过渡提供了最完备的物质准备"
        ],
        "answer": "A",
        "analysis": ""
    },
    {
        "id": "20230907231886577",
        "title": "国家垄断资本主义对资本主义基本矛盾",
        "option": [
            "可以完全克服；",
            "不可能克服；",
            "有可能克服；",
            "可以克服其大部分"
        ],
        "answer": "B",
        "analysis": ""
    },
    {
        "id": "202309072318852599",
        "title": "垄断资本主义国家对经济的宏观管理与调节是代表着",
        "option": [
            "大垄断资本家的经济利益；",
            "中小资本家的经济利益；",
            "垄断资产阶级的整体利益；",
            "全体劳动人民的共同利益"
        ],
        "answer": "A",
        "analysis": ""
    },
    {
        "id": "202309072318140303",
        "title": "国家垄断资本主义对经济的宏观调节，代表着",
        "option": [
            "极少数金融寡头的经济利益；",
            "国有企业的经济利益",
            "中小资本家的利益；",
            "垄断资产阶级的整体利益"
        ],
        "answer": "D",
        "analysis": ""
    },
    {
        "id": "202309072318255619",
        "title": "垄断资本主义国家的计划管理是",
        "option": [
            "从根本上解决了资本主义的基本矛盾；",
            "消除了资本主义经济危机；",
            "导致资本主义向社会主义和平过渡；",
            "使生产无政府状态得到一定的缓解"
        ],
        "answer": "D",
        "analysis": ""
    },
    {
        "id": "202309072318759123",
        "title": "资产阶级国家参与社会再生产的目的是",
        "option": [
            "实现供求总量平衡，调整优化经济结构；",
            "合理配置资源，提高社会生产力；",
            "实现充分就业；",
            "保证垄断资产阶级获得高额垄断利润"
        ],
        "answer": "D",
        "analysis": ""
    },
    {
        "id": "202309072318892178",
        "title": "当代西方发达国家经济社会制度的性质是",
        "option": [
            "私人垄断资本主义；",
            "自由竞争资本主义；",
            "国家垄断资本主义；",
            "后资本主义"
        ],
        "answer": "C",
        "analysis": ""
    },
    {
        "id": "202309072318331190",
        "title": "资本输出的实质是",
        "option": [
            "发达国家帮助发展中国家发展经济的手段；",
            "发达国家带动其商品输出的手段；",
            "发达国与发展中国家的一种互助互利关系；",
            "金融资本掠夺、剥削和奴役其它国家和人民的重要手段"
        ],
        "answer": "D",
        "analysis": ""
    },
    {
        "id": "202309072318528127",
        "title": "自由竞争资本主义阶段，资本主义国家对外经济联系的主要方式是",
        "option": [
            "资本输出；",
            "商品输出；",
            "对外经济援助；",
            "技术输出"
        ],
        "answer": "B",
        "analysis": ""
    },
    {
        "id": "202309072318503020",
        "title": "资本输出的财力基础是",
        "option": [
            "自由竞争；",
            "垄断；",
            "社会化大生产；",
            "大量过剩资本"
        ],
        "answer": "D",
        "analysis": ""
    },
    {
        "id": "202309072318168766",
        "title": "各国最大的垄断组织从经济上瓜分世界表明__产生",
        "option": [
            "国家垄断资本主义；",
            "国际垄断同盟；",
            "金融寡头；",
            "资本输出"
        ],
        "answer": "B",
        "analysis": ""
    },
    {
        "id": "202309072318329704",
        "title": "垄断资本主义国家从经济上瓜分世界市场的手段是",
        "option": [
            "资本输出；",
            "商品输出；",
            "占领殖民地；",
            "建立国际垄断同盟"
        ],
        "answer": "D",
        "analysis": ""
    },
    {
        "id": "202309072318644100",
        "title": "国际垄断同盟在经济上瓜分世界的依据是",
        "option": [
            "军备力量的强弱；",
            "资本和经济实力的大小；",
            "国土的大小；",
            "人口的多少"
        ],
        "answer": "B",
        "analysis": ""
    },
    {
        "id": "202309072318599647",
        "title": "自由竞争资本主义阶段，资本国际化的主要形式是",
        "option": [
            "生产资本；",
            "商业资本；",
            "借贷资本；",
            "国家资本"
        ],
        "answer": "B",
        "analysis": ""
    },
    {
        "id": "202309072318272243",
        "title": "垄断资本主义时期，资本国际化的主要形式是",
        "option": [
            "商业资本国际化；",
            "借贷资本国际化；",
            "产业资本国际化；",
            "金融资本国际化"
        ],
        "answer": "C",
        "analysis": ""
    },
    {
        "id": "202309072318167400",
        "title": "第二资世界大战后，出现了一种新型的国际垄断组织",
        "option": [
            "跨国公司；",
            "国际卡特尔；",
            "国际辛迪加；",
            "国际托拉斯"
        ],
        "answer": "A",
        "analysis": ""
    },
    {
        "id": "202309072318948704",
        "title": "跨国公司是",
        "option": [
            "发达国家共同出资建立的；",
            "是由一国或一国的垄断组织为主建立起来的；",
            "是多国垄断组织的联盟；",
            "有关国际经济组织投资建立的"
        ],
        "answer": "B",
        "analysis": ""
    },
    {
        "id": "202309072318997695",
        "title": "经济全球化",
        "option": [
            "是生产力高度发展的产物；",
            "与生产力高度发展无关；",
            "阻碍了生产力高度发展；",
            "是少数国家推动的结果"
        ],
        "answer": "A",
        "analysis": ""
    },
    {
        "id": "202309072318805118",
        "title": "生产国际化和资本国际化是以",
        "option": [
            "科学技术的发展为基础的；",
            "国际分工的发展为基础的；",
            "经济全球化的发展为基础的；",
            "高新技术产业的发展为基础的"
        ],
        "answer": "A",
        "analysis": ""
    },
    {
        "id": "202309072318645154",
        "title": "经济全球化的实质是",
        "option": [
            "发达资本主义国家占优势、为主导的经济运动；",
            "发展中国家占优势、为主导的经济运动；",
            "对外开放国家占优势、为主导的经济运动；",
            "各国平等互利的经济运动"
        ],
        "answer": "A",
        "analysis": ""
    },
    {
        "id": "202309072318163639",
        "title": "经济全球化对世界经济发展 ",
        "option": [
            "只有消极的影响；",
            "只有积极的影响；",
            "无所谓积极与消极的影响；",
            "既有积极也有消极的影响"
        ],
        "answer": "D",
        "analysis": ""
    },
    {
        "id": "202309072318834947",
        "title": "成立最早、影响最大的区域经济集团是",
        "option": [
            "欧洲联盟；",
            "北美自由贸易区；",
            "亚太经济合作组织；",
            "东南亚经济合作组织"
        ],
        "answer": "A",
        "analysis": ""
    },
    {
        "id": "202309072318246205",
        "title": "组建跨国联盟反映了跨国公司主导作用",
        "option": [
            "增强；",
            "减弱；",
            "不变；",
            "将消失"
        ],
        "answer": "A",
        "analysis": ""
    },
    {
        "id": "202309072318772622",
        "title": "经济全球化的进程明显加快的原因有很多，但不包括",
        "option": [
            "第三次科学技术革命向纵深发展；",
            "国际贸易自由化程度大大提高；",
            "国际资本流动的大幅度增加；",
            "自由竞争资本主义阶段的出现"
        ],
        "answer": "D",
        "analysis": ""
    },
    {
        "id": "20230907231840215",
        "title": "经济全球化的内容有许多，但不包括",
        "option": [
            "生产全球化；",
            "贸易全球化；",
            "殖民体系全球化；",
            "资本全球化"
        ],
        "answer": "C",
        "analysis": ""
    },
    {
        "id": "202309072318642785",
        "title": "下列不属于经济全球化发展趋势的选项是",
        "option": [
            "市场经济成为全球经济体制；",
            "区域经济集团化日益发展；",
            "跨国公司的主导作用增强；",
            "国际经济新秩序的建立"
        ],
        "answer": "D",
        "analysis": ""
    },
    {
        "id": "202309072318961772",
        "title": "跨国公司之间的联盟",
        "option": [
            "推动了经济全球化的发展；",
            "阻碍了经济全球化的发展；",
            "与经济全球化的发展无关；",
            "是一种反全球化运动"
        ],
        "answer": "A",
        "analysis": ""
    },
    {
        "id": "202309072318772049",
        "title": "经济全球化的实质决定了它的发展必然",
        "option": [
            "有利于所有国家；",
            "有利于发达资本主义国家；",
            "有利于发展中国家；",
            "有利于社会主义国家"
        ],
        "answer": "B",
        "analysis": ""
    },
    {
        "id": "202309072318429786",
        "title": "经济全球化带给发达国家的好处很多，但不包括",
        "option": [
            "从世界各地获得大量的利润；",
            "降低其生产成本；",
            "扩大了贸易逆差；",
            "加强对国际金融市场的控制"
        ],
        "answer": "C",
        "analysis": ""
    },
    {
        "id": "202309072318185298",
        "title": "发达资本主义国家之间的经济关系表现为",
        "option": [
            "矛盾与协调并存；",
            "只有协调没有矛盾",
            "只有矛盾没有协调；",
            "协调与妥协并存"
        ],
        "answer": "A",
        "analysis": ""
    },
    {
        "id": "202309072318230420",
        "title": "不属于国际经济旧秩序内容的是",
        "option": [
            "以不合理的国际分工为基础的国际生产体系；",
            "以不平等交换为基础的国际贸易体系；",
            "以自由平等交换为基础的国际贸易体系；",
            "以垄断资本为基础的国际金融体系"
        ],
        "answer": "C",
        "analysis": ""
    },
    {
        "id": "202309072318393141",
        "title": "垄断资本主义条件下经济迅速发展和停滞两种趋势的根源在于",
        "option": [
            "垄断统治；",
            "资本输出；",
            "国家垄断资本主义的产生；",
            "对技术进步的阻碍"
        ],
        "answer": "A",
        "analysis": ""
    },
    {
        "id": "202309072318786413",
        "title": "资本主义国家的福利制度",
        "option": [
            "提高了劳动者的实际工资；",
            "表明资产阶级同劳动人民的利益是一致的；",
            "减轻了对雇佣劳动者的剥削；",
            "没有减轻对雇佣劳动者的剥削，是羊毛出在羊身上"
        ],
        "answer": "D",
        "analysis": ""
    },
    {
        "id": "202309072318565528",
        "title": "社会主义产生以前的阶段是",
        "option": [
            "股份公司；",
            "垄断资本主义；",
            "国家垄断资本主义；",
            "国际垄断同盟"
        ],
        "answer": "C",
        "analysis": ""
    },
    {
        "id": "202309072318512231",
        "title": "国家垄断资本主义使生产、资本、管理社会化程度空前提高这表明",
        "option": [
            "为由资本主义向社会主义过渡准备了最充分的物质基础；",
            "经济危机彻底得以消除；",
            "资本主义基本矛盾得到解决；",
            "资本主义制度具有生命力"
        ],
        "answer": "A",
        "analysis": ""
    },
    {
        "id": "202309072318653947",
        "title": "资本主义经济政治发展不平衡决定了社会主义革命只能",
        "option": [
            "在发达资本主义国家首先取得胜利；",
            "在所有资本主义国家同时取得胜利；",
            "在一国或几国首先取得胜利；",
            "在所有不发达资本主义国家同时取得胜利"
        ],
        "answer": "C",
        "analysis": ""
    },
    {
        "id": "202309072318285186",
        "title": "资本主义积累过程发展的历史趋势是",
        "option": [
            "缓和并最终解决资本主义的基本矛盾；",
            "社会主义取代资本主义；",
            "全世界同时建立生产资料公有制；",
            "全世界都进入资本主义制度"
        ],
        "answer": "B",
        "analysis": ""
    },
    {
        "id": "202309072318325619",
        "title": "解决资本主义基本矛盾的唯一途径是",
        "option": [
            "用垄断代替自由竞争；",
            "用国家垄断资本主义代替私人垄断资本主义；",
            "用国际垄断代替国家垄断资本主义；",
            "用社会主义制度代替资本主义制度"
        ],
        "answer": "D",
        "analysis": ""
    },
    {
        "id": "202309072318858159",
        "title": "垄断是",
        "option": [
            "在自由竞争和生产集中基础上发展起来的；",
            "帝国主义的经济实质；",
            "资本主义大企业或企业联合控制一个或几个部门的生产和市场；",
            "帝国主义最基本的经济特征；",
            "造成帝国主义寄生性或腐朽性的根本原因"
        ],
        "answer": "ABCDE",
        "analysis": ""
    },
    {
        "id": "202309072318302785",
        "title": "垄断组织比较发达的一般形式有",
        "option": [
            "短期价格协定；",
            "卡特尔；",
            "辛迪加；",
            "托拉斯；",
            "康采恩"
        ],
        "answer": "BCDE",
        "analysis": ""
    },
    {
        "id": "20230907231811081",
        "title": "战后国内垄断得到迅速发展，这表现在",
        "option": [
            "垄断财团的实力增长；",
            "金融资本与国家政权更加密切地溶合；",
            "金融寡头的统治进一步加强；",
            "财团的家族色彩日趋淡薄；",
            "出现了康采恩这种垄断组织形式"
        ],
        "answer": "ABCD",
        "analysis": ""
    },
    {
        "id": "202309072318234367",
        "title": "垄断价格是",
        "option": [
            "资本家可以获得超额利润的价格；",
            "垄断组织凭其垄断地位规定的一种市场价格；",
            "由垄断高价和垄断低价构成的；",
            "保证垄断利润的主要手段；",
            "遵循“价格领头制”原则制定的"
        ],
        "answer": "ABCDE",
        "analysis": ""
    },
    {
        "id": "202309072318595782",
        "title": "垄断高价和垄断低价并不否定价值规律，因为",
        "option": [
            "垄断价格只是使价值规律改变了表现形式；",
            "按垄断低价买卖的行为，仍然是等价交换；",
            "从整个社会看，商品的价格总额和价值总额是一致的；",
            "垄断高价是把其他商品生产者的一部分利润转移到垄断高价的商品上；",
            "垄断高价和垄断低价不能完全离开商品的价值"
        ],
        "answer": "ACDE",
        "analysis": ""
    },
    {
        "id": "202309072318897787",
        "title": "第二次世界大战后，垄断发展的新现象有",
        "option": [
            "垄断资本的跨部门发展；",
            "垄断取代了竞争；",
            "私人垄断资本加速向国家垄断转变；",
            "大型企业间的联合与兼并加剧；",
            "跨国公司成为垄断组织的主要形式"
        ],
        "answer": "ACDE",
        "analysis": ""
    },
    {
        "id": "202309072318713125",
        "title": "垄断时期竞争的手段主要有",
        "option": [
            "政治手段；",
            "经济手段；",
            "暴力手段；",
            "欺骗、讹诈和盗窃情报；",
            "掠夺市场、原料、信贷和运输条件"
        ],
        "answer": "ABCDE",
        "analysis": ""
    },
    {
        "id": "202309072318110270",
        "title": "垄断时期竞争的特点主要是",
        "option": [
            "目的是获得垄断高额利润；",
            "手段更加多样化；",
            "范围涉及政治领域；",
            "程度更加激烈；",
            "后果造成社会劳动的浪费和引起帝国主义战争"
        ],
        "answer": "ABCDE",
        "analysis": ""
    },
    {
        "id": "202309072318737509",
        "title": "垄断竞争是",
        "option": [
            "垄断组织内部的竞争；",
            "垄断组织之间的竞争；",
            "垄断组织与“局外企业”之间的竞争；",
            "“局外企业”之间的竞争；",
            "“局外企业”内部的竞争"
        ],
        "answer": "ABC",
        "analysis": ""
    },
    {
        "id": "202309072318653196",
        "title": "垄断利润来自",
        "option": [
            "垄断企业雇佣工人创造的剩余价值；",
            "通过高价出售消费品，把消费者的一部分收入转化为垄断利润；",
            "资产阶级国家对国民收入作有利于垄断资本家的再分配；",
            "通过向非垄断企业低价购买生产资料，占有它们的一部分利润；",
            "通过国际不等价交换，占有其他国家人民创造的一部分价值"
        ],
        "answer": "ABCDE",
        "analysis": ""
    },
    {
        "id": "202309072318325790",
        "title": "银行业集中和垄断的形成是",
        "option": [
            "以工业的集中和垄断为基础；",
            "以金融资本的形成为基础；",
            "以金融寡头的统治为基础；",
            "银行资本家之间竞争的结果；",
            "银行和工业之间竞争的结果"
        ],
        "answer": "ADE",
        "analysis": ""
    },
    {
        "id": "202309072318603577",
        "title": "战前国际垄断同盟的主要形式是",
        "option": [
            "短期价格协定",
            "卡特尔；",
            "辛迪加；",
            "托拉斯；",
            "混合联合公司"
        ],
        "answer": "BCDE",
        "analysis": ""
    },
    {
        "id": "202309072318866007",
        "title": "战后国际垄断同盟的主要形式是",
        "option": [
            "托拉斯；",
            "康采恩；",
            "混合联合企业；",
            "跨国公司；",
            "以国家形式出现的国际垄断同盟"
        ],
        "answer": "DE",
        "analysis": ""
    },
    {
        "id": "202309072318797905",
        "title": "国家垄断资本主义是 ",
        "option": [
            "资本主义矛盾发展的产物；",
            "私人垄断组织与国家政权相结合的资本主义；",
            "国家资本主义；",
            "社会主义最完备的物质基础；",
            "社会主义的入口"
        ],
        "answer": "ABDE",
        "analysis": ""
    },
    {
        "id": "202309072318551400",
        "title": "政府出面组织的国际垄断同盟的主要形式有",
        "option": [
            "就某种商品的生产和销售达成的国际经济协定；",
            "就一个部门的生产和销售达成的国际经济协定；",
            "在国民经济领域内建立的国际垄断同盟；",
            "跨国公司；",
            "混合联合企业"
        ],
        "answer": "ABC",
        "analysis": ""
    },
    {
        "id": "202309072318277962",
        "title": "垄断组成的生产全面社会化包括",
        "option": [
            "生产资料使用社会化；",
            "生产过程社会化；",
            "产品社会化；",
            "管理社会化；",
            "资本社会化"
        ],
        "answer": "ABCDE",
        "analysis": ""
    },
    {
        "id": "20230907231838345",
        "title": "资本主义生产关系在其自身范围内调整的表现形式是",
        "option": [
            "从自由竞争阶段发展到垄断阶段；",
            "从私人垄断主义发展到国家垄断资本主义；",
            "股份公司的出现；",
            "国民经济计划化的实行；",
            "社会福利制度的实施"
        ],
        "answer": "ABCE",
        "analysis": ""
    },
    {
        "id": "202309072318855281",
        "title": "国家垄断资本主义的局限性体现在",
        "option": [
            "它是资本主义生产关系的局部调整；",
            "它暂时缓和了经济和社会矛盾；",
            "它不能从根本上消除资本主义的基本矛盾；",
            "它代表着垄断资产阶级的整体利益；",
            "它没有改变垄断资本主义的性质"
        ],
        "answer": "ABCDE",
        "analysis": ""
    },
    {
        "id": "202309072318611717",
        "title": "当代资本主义国家的宏观调控",
        "option": [
            "避免了经济危机；",
            "在一定程度上削平经济高涨时的尖峰，垫起经济萧条时的低谷；",
            "减弱了经济周期的震荡；",
            "仅仅是治标的办法；",
            "从根本上解决了资本主义经济周期中各种内的、深刻的矛盾"
        ],
        "answer": "BCD",
        "analysis": ""
    },
    {
        "id": "202309072318993074",
        "title": "资产阶级国家与私人共有的垄断资本形式是通过以下途径产生的",
        "option": [
            "国家购买私人垄断企业的一部分股份；",
            "国外垄断资本投资；",
            "国有企业吸收一部分私人垄断资本的投资；",
            "两个以上的垄断组织联合；",
            "国家与私人垄断资本联合投资兴建企业"
        ],
        "answer": "ACE",
        "analysis": ""
    },
    {
        "id": "202309072318151643",
        "title": "资本主义国家干预和调节经济的目标有",
        "option": [
            "经济总量基本平衡；",
            "物价总水平基本稳定；",
            "充分就业；",
            "国际收支基本平衡；",
            "经济稳定增长"
        ],
        "answer": "ABCDE",
        "analysis": ""
    },
    {
        "id": "202309072318901165",
        "title": "垄断条件下资本输出的必然性在于",
        "option": [
            "资本输出是帝国主义的本质要求和特征；",
            "资本输出使经济落后国家经济畸形化；",
            "垄断统治在国内出现大量过剩资本；",
            "经济落后国家是帝国主义国家的附庸；",
            "许多经济落后国家卷入资本主义世界市场"
        ],
        "answer": "AC",
        "analysis": ""
    },
    {
        "id": "202309072318163329",
        "title": "资本输出是",
        "option": [
            "帝国主义垂死性的根本原因；",
            "金融资本对外扩张的主要手段；",
            "帝国主义的一大经济特征；",
            "资本主义国际分工和经济联系的基础；",
            "资本主义国家政府或资本家对外的投资或贷款"
        ],
        "answer": "ABCDE",
        "analysis": ""
    },
    {
        "id": "202309072318745384",
        "title": "从资本输出的主体来划分，资本输出的形式有",
        "option": [
            "借贷资本输出；",
            "生产资本输出；",
            "商品资本输出；",
            "私人资本输出；",
            "国家资本输出"
        ],
        "answer": "DE",
        "analysis": ""
    },
    {
        "id": "202309072318645964",
        "title": "从资本形态上划分，资本输出的形式有",
        "option": [
            "借贷资本输出；",
            "生产资本输出；",
            "商品资本输出；",
            "私人资本输出；",
            "国家资本输出"
        ],
        "answer": "ABC",
        "analysis": ""
    },
    {
        "id": "202309072318412792",
        "title": "二战后资本输出量剧增，并出现了一些新特点，主要有",
        "option": [
            "资本流向上主要是发达国家向经济落后国家输出；",
            "资本流向上主要是发达国家之间相互投资；",
            "私人资本输出比国家资本输出增长更快；",
            "国家资本输出比私人资本输出增出更快；",
            "向发展中国家的资本输出大多采取援助的方式"
        ],
        "answer": "ACE",
        "analysis": ""
    },
    {
        "id": "202309072318968308",
        "title": "资本输出的后果表现在",
        "option": [
            "使经济落后国自然经济瓦解和资本主义经济发展；",
            "使经济落后国经济畸形化和依赖性增强；",
            "使经济落后国政治上从属于帝国主义国家；",
            "引起资本输出国在一定程度上经济发展的停滞；",
            "引起帝国主义国家之间矛盾加剧"
        ],
        "answer": "BCDE",
        "analysis": ""
    },
    {
        "id": "202309072318427672",
        "title": "对于输入国来说，资本输出",
        "option": [
            "促进了输入国自然经济的瓦解和商品经济的发展；",
            "带动输入国建设了一些经济发展所必需的基础设施；",
            "对输入国民族经济的发展没有任何益处；",
            "给输入国带来一系列社会经济问题；",
            "有可能造成输入国经济片面畸形发展"
        ],
        "answer": "ABDE",
        "analysis": ""
    },
    {
        "id": "202309072318137725",
        "title": "对于输出国来说，资本输出",
        "option": [
            "为过剩资本找到了出路，并带来巨额利润和利息；",
            "是输出国控制输入国的重要手段；",
            "是输出国扩大商品出口的主要手段；",
            "强化了金融资本在世界上的统治地位；",
            "使输出国成为食利国并导致输出国国内经济发展缓慢"
        ],
        "answer": "ABCDE",
        "analysis": ""
    },
    {
        "id": "20230907231814761",
        "title": "跨国公司",
        "option": [
            "是对外直接投资，在国外设立子公司或分支机构的大型垄断企业；",
            "从事跨国生产、销售或金融等各种经营活动；",
            "以获取高额垄断利润为目的；",
            "是战后国际垄断组织的主要形式；",
            "是经济全球化的必然要求"
        ],
        "answer": "ABCDE",
        "analysis": ""
    },
    {
        "id": "202309072318230840",
        "title": "第二次世界大战后跨国公司的迅速发展",
        "option": [
            "是产业资本国际化的必然要求；",
            "是垄断大资本对外扩张和掠夺的工具；",
            "成为国际垄断组织的主要形式；",
            "是攫取高额垄断利润的需要；",
            "是资本输出的需要"
        ],
        "answer": "ABCDE",
        "analysis": ""
    },
    {
        "id": "202309072318601735",
        "title": "当代国际垄断组织的主要形式是",
        "option": [
            "国际卡特尔；",
            "跨国公司；",
            "国家垄断资本主义的国际垄断同盟；",
            "国际辛迪加；",
            "国际托拉斯"
        ],
        "answer": "BC",
        "analysis": ""
    },
    {
        "id": "202309072318455689",
        "title": "近二、三十年贸易全球化加快发展的原因是",
        "option": [
            "世界资本市场和国际金融体系大发展；",
            "各国间产业分工的深化使产品交流的必要性大大增加；",
            "高效率、大批量生产要求扩大国际贸易规模；",
            "人们生活水平提高增加了对各国产品的需求；",
            "更便捷更灵活的国际贸易方式的发现"
        ],
        "answer": "ABCDE",
        "analysis": ""
    },
    {
        "id": "202309072318108809",
        "title": "战后以来，对世界经济和国际经济秩序产生较大影响的国际经济经组织主要有",
        "option": [
            "海牙国际法院；",
            "国际货币基金组织；",
            "世界银行；",
            "世界贸易组织；",
            "北大西洋公约组织"
        ],
        "answer": "BCD",
        "analysis": ""
    },
    {
        "id": "202309072318168252",
        "title": "经济全球化的内容主要包括",
        "option": [
            "商品全球化；",
            "货币全球化；",
            "生产全球化；",
            "贸易全球化；",
            "资本全球化"
        ],
        "answer": "ABCDE",
        "analysis": ""
    },
    {
        "id": "202309072318781230",
        "title": "经济全球化发展趋势的主要表现是",
        "option": [
            "市场经济成为全球经济体制；",
            "区域经济集团化日益发展；",
            "跨国公司的主导作用增强；",
            "几乎所有国家都被卷入了市场经济潮流之中；",
            "劳动力在全球范围内实现自由流动"
        ],
        "answer": "ABCDE",
        "analysis": ""
    },
    {
        "id": "202309072318357707",
        "title": "经济全球化",
        "option": [
            "与民族经济利益是对立的；",
            "会威胁到民族社会的凝聚力和认同；",
            "要求世界各国进行密切的分工合作；",
            "要求不要保护民族和国家的经济利益；",
            "要求提高民族和国家自身的竞争力"
        ],
        "answer": "BCE",
        "analysis": ""
    },
    {
        "id": "20230907231863900",
        "title": "资产阶级推动改良主义的措施主要有",
        "option": [
            "收买本国工人阶级中少数上层分子和工人领袖从内部分裂破坏工人运动；",
            "通过推行福利政策，举办多种福利事业来缓和阶级矛盾；",
            "推行“劳资合作”、“工人参加管理”等措施，来调动工人的积极性；",
            "宣扬“资本民主化”、“人民资本主义”思想；",
            "发放小额股票，鼓励工人购买以此宣扬人人都是企业“主人”"
        ],
        "answer": "BCDE",
        "analysis": ""
    },
    {
        "id": "202309072318125700",
        "title": "资本主义经济政治发展不平衡导致社会主义革命",
        "option": [
            "可能在一切资本主义国家同时取得胜利；",
            "可能在资本主义最发达国家取得胜利；",
            "肯定在发达资本主义国家同时取得胜利；",
            "只能在垄断资本主义统治链条最薄弱环节取得胜利；",
            "只能在一个或几个资本主义国家首先取得胜利"
        ],
        "answer": "DE",
        "analysis": ""
    },
    {
        "id": "202309072318636584",
        "title": "社会主义取代资本主义将是一个长期的历史过程，这是由于",
        "option": [
            "资本主义基本矛盾的运动具有复杂性和曲折性；",
            "资本主义生产关系的调整，在一定程度上还能容纳生产力继续发展；",
            "资本主义已经积累了雄厚的经济实力和丰富的统治经验；",
            "资本主义经济和政治发展不平衡规律的作用；",
            "社会主义制度的巩固和完善需要一个历史过程",
            "BCDE"
        ],
        "answer": "ABCDE",
        "analysis": ""
    }
]