[
    {
        "id": "202309081832287316",
        "title": "哲学的基本问题是  ",
        "option": [
            "社会和自然的关系问题",
            "思维与存在的关系问题",
            "政治和经济的关系问题",
            "实践和理论的关系问题"
        ],
        "answer": "B",
        "analysis": ""
    },
    {
        "id": "202309081832422644",
        "title": "马克思主义认为，哲学是  ",
        "option": [
            "人们自发形成的世界观",
            "理论化、系统化的世界观",
            "科学的世界观",
            "无产阶级的世界观"
        ],
        "answer": "B",
        "analysis": ""
    },
    {
        "id": "202309081832100954",
        "title": "肯定思维和存在有同一性，这是  ",
        "option": [
            "辩证法的观点",
            "形而上学的观点",
            "唯心主义的观点",
            "可知论的观点"
        ],
        "answer": "D",
        "analysis": ""
    },
    {
        "id": "202309081832225901",
        "title": "唯心主义的基本形式是  ",
        "option": [
            "客观唯心主义与主观唯心主义",
            "一元论唯心主义与二元论唯心主义",
            "经验论唯心主义与唯理论唯心主义",
            "辩证唯心主义与形而上学唯心主义"
        ],
        "answer": "A",
        "analysis": ""
    },
    {
        "id": "202309081832726745",
        "title": "下列观点属于主观唯心主义的是  ",
        "option": [
            "心外无物，心外无理",
            "理在气中，理随事变",
            "富贵在天，死生由命",
            "理在事先，事随理变"
        ],
        "answer": "A",
        "analysis": ""
    },
    {
        "id": "202309081832613187",
        "title": "下列属于客观唯心主义的是  ",
        "option": [
            "存在就是被感知",
            "物是感觉的复合",
            "意识是万物的本原",
            "理在事先"
        ],
        "answer": "D",
        "analysis": ""
    },
    {
        "id": "202309081832611267",
        "title": "“存在就是被感知”是  ",
        "option": [
            "机械唯物主义观点",
            "客观唯物主义观点",
            "朴素唯物主义观点",
            "主观唯心主义观点"
        ],
        "answer": "D",
        "analysis": ""
    },
    {
        "id": "202309081832215846",
        "title": "古代朴素唯物主义把世界的本原归结为  ",
        "option": [
            "绝对观念",
            "客观实在",
            "理念世界",
            "水、火等“原初”物质"
        ],
        "answer": "D",
        "analysis": ""
    },
    {
        "id": "202309081832683651",
        "title": "中国古代哲学家荀子说：“天行有常，不为尧存，不为桀亡。”这是一种  ",
        "option": [
            "宿命论观点",
            "唯意志论观点",
            "机械唯物论观点",
            "朴素唯物论观点"
        ],
        "answer": "D",
        "analysis": ""
    },
    {
        "id": "202309081832789032",
        "title": "在马克思主义哲学产生以前不曾存在  ",
        "option": [
            "唯物主义和唯心主义的斗争",
            "唯物史观和唯心史观的斗争",
            "辩证法和形而上学的斗争",
            "可知论和不可知论的斗争"
        ],
        "answer": "B",
        "analysis": ""
    },
    {
        "id": "202309081832584784",
        "title": "判断一种哲学是否是“真正的哲学”取决于它  ",
        "option": [
            "是否坚持唯心论",
            "是否坚持辩证法",
            "是否坚持唯物论",
            "是否是时代精神的精华"
        ],
        "answer": "D",
        "analysis": ""
    },
    {
        "id": "202309081832995050",
        "title": "哲学上的一元论就是承认  ",
        "option": [
            "世界是物质",
            "世界在本质上是精神",
            "世界是发展的",
            "世界的本原只有一个"
        ],
        "answer": "D",
        "analysis": ""
    },
    {
        "id": "202309081832224491",
        "title": "旧唯物主义不能彻底战胜唯心主义的根本原因是  ",
        "option": [
            "主张物质的决定作用",
            "否认意识的能动作用",
            "无法驳斥唯心主义狡猾的诡辩",
            "不懂得科学的实践观点"
        ],
        "answer": "D",
        "analysis": ""
    },
    {
        "id": "202309081832487782",
        "title": "对哲学基本问题第一个方面内容的不同回答是  ",
        "option": [
            "划分唯物主义和唯心主义的标准",
            "划分辩证法和形而上学的标准",
            "划分可知论和不可知论的标准",
            "划分辩证唯物主义和形而上学唯物主义的标准"
        ],
        "answer": "A",
        "analysis": ""
    },
    {
        "id": "202309081832534875",
        "title": "马克思主义哲学和具体科学的关系属于  ",
        "option": [
            "内容和形式的关系",
            "整体和部分的关系",
            "原因和结果的关系",
            "共性和个性的关系"
        ],
        "answer": "D",
        "analysis": ""
    },
    {
        "id": "202309081832544023",
        "title": "物质的唯一特性是   ",
        "option": [
            "运动变化性",
            "客观实在性",
            "具体性",
            "可感知性"
        ],
        "answer": "B",
        "analysis": ""
    },
    {
        "id": "202309081832994709",
        "title": "物质无非是各种物的总和，是从这种总和抽象出来的。这种观点属于  ",
        "option": [
            "辩证唯物主义物质观",
            "形而上学唯物主义物质观",
            "庸俗唯物主义物质观",
            "朴素唯物主义物质观"
        ],
        "answer": "A",
        "analysis": ""
    },
    {
        "id": "202309081832691267",
        "title": "运动是物质的存在方式。这是对运动的  ",
        "option": [
            "唯心主义理解",
            "直观唯物主义理解",
            "辩证唯物主义理解",
            "庸俗唯物主义理解"
        ],
        "answer": "C",
        "analysis": ""
    },
    {
        "id": "202309081832318042",
        "title": "在物质和运动关系问题上，形而上学唯物主义的错误是  ",
        "option": [
            "夸大运动的绝对性",
            "设想无物质的运动",
            "否认静止的存在",
            "设想无运动的物质"
        ],
        "answer": "D",
        "analysis": ""
    },
    {
        "id": "202309081832447432",
        "title": "在物质和运动关系问题上，唯心主义哲学的错误是  ",
        "option": [
            "设想无物质的运动",
            "否认运动的存在",
            "设想无运动的物质",
            "否认静止的存在"
        ],
        "answer": "A",
        "analysis": ""
    },
    {
        "id": "2023090818328123",
        "title": "运动和静止的关系是  ",
        "option": [
            "现象和本质的关系",
            "一般和个别的关系",
            "绝对和相对的关系",
            "抽象和具体的关系"
        ],
        "answer": "C",
        "analysis": ""
    },
    {
        "id": "202309081832684380",
        "title": "时间和空间  ",
        "option": [
            "同物质运动无关",
            "是一种先验的形式",
            "是运动着的物质本身",
            "是运动着的物质的存在方式"
        ],
        "answer": "D",
        "analysis": ""
    },
    {
        "id": "202309081832512663",
        "title": "从动物心理发展到人的意识的决定性环节是   ",
        "option": [
            "手脚分工",
            "语言的产生",
            "社会的出现",
            "劳动"
        ],
        "answer": "D",
        "analysis": ""
    },
    {
        "id": "202309081832296108",
        "title": "意识是人脑的机能，表现  ",
        "option": [
            "人脑是意识的源泉",
            "意识是人脑自生的",
            "意识是人脑的分泌物",
            "人脑是产生意识的物质器官"
        ],
        "answer": "D",
        "analysis": ""
    },
    {
        "id": "202309081832951419",
        "title": "假定一切物质都具有在本质上跟感觉相近的特性，反映的特性，这是合乎逻辑的。这种观点  ",
        "option": [
            "辩证唯物主义观点",
            "主观唯物主义观点",
            "朴素唯物主义观点",
            "客观唯物主义观点"
        ],
        "answer": "A",
        "analysis": ""
    },
    {
        "id": "202309081832515389",
        "title": "“观念的东西不外是移入人脑并在人的头脑中改造过的物质的东西而已。”这一观点是",
        "option": [
            "客观唯心主义观点",
            "朴素唯物主义观点",
            "唯意志主义观点",
            "辩证唯物主义观点"
        ],
        "answer": "D",
        "analysis": ""
    },
    {
        "id": "202309081832743547",
        "title": "列宁关于“人的意识不仅反映客观世界，而且创造客观世界”的说法  ",
        "option": [
            "夸大了意识的作用",
            "正确地指出了意识的能动作用",
            "具有唯意志主义的倾向",
            "是主观唯心主义的表现"
        ],
        "answer": "B",
        "analysis": ""
    },
    {
        "id": "202309081832278705",
        "title": "世界的真正统一性在于它的  ",
        "option": [
            "存在性",
            "运动性",
            "物质性",
            "可知性"
        ],
        "answer": "C",
        "analysis": ""
    },
    {
        "id": "202309081832552410",
        "title": "意识能动性实现的根本途径是  ",
        "option": [
            "社会实践",
            "主观努力",
            "客观规律",
            "先进的物质手段"
        ],
        "answer": "A",
        "analysis": ""
    },
    {
        "id": "202309081832267117",
        "title": "正确发挥意识能动作用的客观前提是  ",
        "option": [
            "个人积极性的发挥",
            "集体智慧的调动",
            "解放思想",
            "对客观规律的正确反映"
        ],
        "answer": "D",
        "analysis": ""
    },
    {
        "id": "202309081832563122",
        "title": "设想脱离物质的运动会导致  ",
        "option": [
            "形而上学",
            "机械唯物论",
            "唯心主义",
            "二元论"
        ],
        "answer": "C",
        "analysis": ""
    },
    {
        "id": "202309081832454934",
        "title": "时间具有一维性，这是指它的  ",
        "option": [
            "可变性",
            "无限性",
            "不可逆性",
            "连续性"
        ],
        "answer": "C",
        "analysis": ""
    },
    {
        "id": "20230908183251863",
        "title": "语言是意识的物质外壳，没有语言就不会有思维和意识，这种观点属于  ",
        "option": [
            "唯心主义",
            "形而上学",
            "马克思主义哲学",
            "历史唯心主义"
        ],
        "answer": "C",
        "analysis": ""
    },
    {
        "id": "202309081832326728",
        "title": "“狼孩”没有意识，这一事实说明  ",
        "option": [
            "意识是生物界长期发展的产物",
            "意识是社会的产物",
            "意识是人脑发展的产物",
            "意识是对客观世界的反映"
        ],
        "answer": "B",
        "analysis": ""
    },
    {
        "id": "2023090818323076",
        "title": "“意识是人脑分泌的特殊物质，”这是  ",
        "option": [
            "辩证唯物主义的观点",
            "机械唯物主义的观点",
            "朴素唯物主义的观点",
            "庸俗唯物主义的观点"
        ],
        "answer": "D",
        "analysis": ""
    },
    {
        "id": "202309081832148927",
        "title": "人工智能的出现和发展证明  ",
        "option": [
            "意识不是人类所特有的现象",
            "物质是意识产生的基础",
            "对人脑机能的认识已经完成",
            "人工思维最终会超过人类思维"
        ],
        "answer": "B",
        "analysis": ""
    },
    {
        "id": "202309081832641752",
        "title": "“动中有静，静中有动”说明  ",
        "option": [
            "物质和运动的统一",
            "绝对运动和相对静止的统一",
            "有限性和无限性的统一",
            "唯物主义和辩证法的统一"
        ],
        "answer": "B",
        "analysis": ""
    },
    {
        "id": "202309081832779680",
        "title": "古希腊哲学家克拉底鲁指出，万物瞬息万变，不可捉摸，人连一次也不能踏进同一条河流。这是一种  ",
        "option": [
            "唯心主义的观点",
            "形而上学的观点",
            "相对主义诡辩论的观点",
            "庸俗进化论的观点"
        ],
        "answer": "C",
        "analysis": ""
    },
    {
        "id": "202309081832211281",
        "title": "能够证明时间、空间的绝对性和相对性相统一的自然科学理论是  ",
        "option": [
            "电磁场理论",
            "原子结构学说",
            "牛顿力学理论",
            "相对论"
        ],
        "answer": "D",
        "analysis": ""
    },
    {
        "id": "202309081832324828",
        "title": "古诗说“王子去求仙，丹成入九天，洞中方七日，世上已千年”。这是用神话形式说明时间  ",
        "option": [
            "是客观的",
            "是有限的",
            "是可知的",
            "是相对的"
        ],
        "answer": "D",
        "analysis": ""
    },
    {
        "id": "20230908183239547",
        "title": "“机不可失，时不再来”指的是  ",
        "option": [
            "时间的连续性",
            "时间的一维性",
            "时间的顺序性",
            "时间的重复性"
        ],
        "answer": "B",
        "analysis": ""
    },
    {
        "id": "202309081832180452",
        "title": "“人有多大胆，地有多大产；不怕办不到，就怕想不到；只要想得到，啥也能办到。”这是  ",
        "option": [
            "主张充分发挥意识能动作用的观点",
            "主观唯心主义的观点",
            "客观唯心主义的观点",
            "朴素唯物主义的观点"
        ],
        "answer": "B",
        "analysis": ""
    },
    {
        "id": "202309081832327607",
        "title": "在客观规律面前，人的主观能动性表现在  ",
        "option": [
            "人可以改变规律",
            "人可以创造规律",
            "人可以消灭规律",
            "人可以认识和利用规律"
        ],
        "answer": "D",
        "analysis": ""
    },
    {
        "id": "202309081832423342",
        "title": "事物的联系和运动之间的关系  ",
        "option": [
            "相互联系构成运动",
            "运动和发展引起质变",
            "发展引起运动",
            "普遍联系和永恒发展"
        ],
        "answer": "A",
        "analysis": ""
    },
    {
        "id": "202309081832485314",
        "title": "唯物辩证法的总特征是   ",
        "option": [
            "量变和质变的观点",
            "辩证否定的观点",
            "联系和发展的观点",
            "对立统一的观点"
        ],
        "answer": "C",
        "analysis": ""
    },
    {
        "id": "202309081832907342",
        "title": "久旱缺雨时，下雨对庄稼生长有益；雨涝成灾时，下雨对庄稼生长有害。这说明",
        "option": [
            "事物的联系是普遍的、无条件的",
            "事物的联系是现实的、具体的",
            "事物的运动是客观的、绝对的",
            "事物发展的根本原因是事物的内部矛盾"
        ],
        "answer": "B",
        "analysis": ""
    },
    {
        "id": "202309081832592710",
        "title": "“割下来的手就不再是人手”这句话体现了  ",
        "option": [
            "形而上学片面的、孤立的观点",
            "辩证法普遍联系的观点",
            "唯心主义的观点",
            "诡辩论的观点"
        ],
        "answer": "B",
        "analysis": ""
    },
    {
        "id": "2023090818322294",
        "title": "唯物辩证法认为发展的实质是  ",
        "option": [
            "事物数量的增加",
            "事物根本性质的变化",
            "事物的一切运动变化",
            "新事物的产生和旧事物的灭亡"
        ],
        "answer": "D",
        "analysis": ""
    },
    {
        "id": "202309081832179875",
        "title": "区分新事物和旧事物的标志在于看它们  ",
        "option": [
            "是不是在新的历史条件下出现的",
            "是不是符合事物发展规律、有强大生命力",
            "是不是具有新形式和新特点",
            "是不是得到绝大多数人的承认"
        ],
        "answer": "B",
        "analysis": ""
    },
    {
        "id": "202309081832926209",
        "title": "质量互变规律揭示了  ",
        "option": [
            "事物发展的动力和源泉",
            "事物发展的状态和过程",
            "事物发展的方向和道路",
            "事物发展的两种趋势"
        ],
        "answer": "B",
        "analysis": ""
    },
    {
        "id": "202309081832182985",
        "title": "质和事物的存在是  ",
        "option": [
            "相互对立的",
            "相互包含的",
            "直接同一的",
            "相互转化的"
        ],
        "answer": "C",
        "analysis": ""
    },
    {
        "id": "202309081832228789",
        "title": "在实际工作中，要注意掌握分寸，防止“过”或“不及”，其关键在于  ",
        "option": [
            "抓住事物的主要矛盾",
            "确定事物的质",
            "认识事物的量",
            "把握事物的度"
        ],
        "answer": "D",
        "analysis": ""
    },
    {
        "id": "202309081832885376",
        "title": "区分量变和质变的根本标志是看  ",
        "option": [
            "事物的变化是否显著",
            "事物的变化是否迅速",
            "事物的某些属性是否发生了变化",
            "事物的变化是否超出度的范围"
        ],
        "answer": "D",
        "analysis": ""
    },
    {
        "id": "202309081832255944",
        "title": "量变的复杂性是指   ",
        "option": [
            "量变的程度发展不同",
            "量变形式的多样性和总的量变过程中有部分质变",
            "质变中有量的扩张",
            "量变有在度的范围内的变化和突破度的范围的变化"
        ],
        "answer": "B",
        "analysis": ""
    },
    {
        "id": "202309081832981758",
        "title": "量变中的阶段性部分质变表现了  ",
        "option": [
            "事物内部各部分之间变化的不平衡性",
            "事物整体与某些构成部分之间变化的不平衡性",
            "事物与事物之间变化的不平衡性",
            "事物的本质属性与非本质属性之间变化的不平衡性"
        ],
        "answer": "D",
        "analysis": ""
    },
    {
        "id": "202309081832327810",
        "title": "量变中的局部性部分质变是  ",
        "option": [
            "事物的本质属性与非本质属性之间变化不平衡性的表现",
            "事物的各个部分之间变化不平衡性的表现",
            "事物的内部矛盾和外部条件变化不平衡性的表现",
            "事物的量和质变化不平衡性的表现"
        ],
        "answer": "B",
        "analysis": ""
    },
    {
        "id": "202309081832793439",
        "title": "揭示事物发展的趋势和道路的规律是  ",
        "option": [
            "对立统一规律",
            "质量互变规律",
            "否定之否定规律",
            "联系和发展规律"
        ],
        "answer": "C",
        "analysis": ""
    },
    {
        "id": "202309081832621253",
        "title": "“肯定和否定相互渗透，在一定意义上，肯定就是否定。”这是一种  ",
        "option": [
            "相对主义诡辩论的观点",
            "唯物辩证法的观点",
            "主观唯心主义的观点",
            "形而上学的观点"
        ],
        "answer": "B",
        "analysis": ""
    },
    {
        "id": "202309081832422906",
        "title": "事物的否定方面是指  ",
        "option": [
            "事物的积极方面",
            "事物的消极方面",
            "事物中维持其存在的方面",
            "事物中促使其灭亡的方面"
        ],
        "answer": "D",
        "analysis": ""
    },
    {
        "id": "202309081832915584",
        "title": "作为辩证的否定的“扬弃”是  ",
        "option": [
            "既保留又继承",
            "彻底抛弃",
            "既克服又保留",
            "矛盾的调和"
        ],
        "answer": "C",
        "analysis": ""
    },
    {
        "id": "202309081832553348",
        "title": "辩证的否定是事物发展的环节，因为辩证的否定  ",
        "option": [
            "把旧事物完全抛弃",
            "使旧事物发生量变",
            "是新事物产生、旧事物灭亡",
            "是从外部强加给事物的"
        ],
        "answer": "C",
        "analysis": ""
    },
    {
        "id": "20230908183236554",
        "title": "否定之否定规律  ",
        "option": [
            "在事物完成一个发展周期时才能完整地表现出来",
            "在事物发展过程中任何一点上都可以表现出来",
            "在事物经过量变和质变两种状态后表现出来",
            "在事物发展过程中经过肯定和否定两个阶段表现出来"
        ],
        "answer": "A",
        "analysis": ""
    },
    {
        "id": "202309081832534499",
        "title": "事物发展的周期性体现了   ",
        "option": [
            "事物发展的直线性与曲折性的统一",
            "事物发展是一个不断地回到出发点的运动",
            "事物发展的周而复始的循环性",
            "事物发展的前进性和曲折性的统一"
        ],
        "answer": "D",
        "analysis": ""
    },
    {
        "id": "202309081832718746",
        "title": "直线论的错误在于只看到  ",
        "option": [
            "事物发展的周期性而否认了前进性",
            "事物发展的前进性而否认了曲折性",
            "事物发展的间接性而否认了连续性",
            "事物发展的曲折性而否认了周期性"
        ],
        "answer": "B",
        "analysis": ""
    },
    {
        "id": "202309081832319848",
        "title": "循环论的错误在于  ",
        "option": [
            "只看到事物发展的普遍性，没有看到事物发展过程的特殊性",
            "只看到事物的绝对运动，没有看到事物的相对静止",
            "只看到事物发展道路的曲折性，没有看到事物发展趋势的前进性",
            "只看到新旧事物之间的连续性，没有看到新旧事物之间的间断性"
        ],
        "answer": "C",
        "analysis": ""
    },
    {
        "id": "20230908183218035",
        "title": "对立统一规律揭示了  ",
        "option": [
            "事物发展的动力和源泉",
            "事物发展的状态和过程",
            "事物发展的方向和道路",
            "事物发展的两种趋向"
        ],
        "answer": "A",
        "analysis": ""
    },
    {
        "id": "202309081832133457",
        "title": "唯物辩证法的实质和核心是  ",
        "option": [
            "对立统一规律",
            "质量互变规律",
            "否定之否定规律",
            "联系和发展的规律"
        ],
        "answer": "A",
        "analysis": ""
    },
    {
        "id": "202309081832178377",
        "title": "辩证法所说的矛盾是指  ",
        "option": [
            "人们思维中的前后不一的自相矛盾",
            "事物之间或事物内部各要素之间的对立统一",
            "对立面之间的相互排斥",
            "事物之间或事物内部各要素之间的相互依赖"
        ],
        "answer": "B",
        "analysis": ""
    },
    {
        "id": "202309081832390594",
        "title": "矛盾的基本属性是  ",
        "option": [
            "普遍性和特殊性",
            "绝对性和相对性",
            "变动性和稳定性",
            "斗争性和同一性"
        ],
        "answer": "D",
        "analysis": ""
    },
    {
        "id": "202309081832251224",
        "title": "我国在社会主义现代化建设中，坚持独立自主、自力更生和对外开放的方针。它的理论依据是  ",
        "option": [
            "矛盾的同一性和斗争性辩证关系的原理",
            "矛盾的普遍性和特殊性辩证关系的原理",
            "事物发展的量变和质变辩证关系的原理",
            "事物发展的内因和外因辩证关系的原理"
        ],
        "answer": "D",
        "analysis": ""
    },
    {
        "id": "202309081832717876",
        "title": "矛盾问题的精髓是  ",
        "option": [
            "矛盾的普遍性和特殊性关系的问题",
            "矛盾的同一性和斗争性关系的问题",
            "主要矛盾和次要矛盾关系的问题",
            "矛盾的主要方面和次要方面关系的问题"
        ],
        "answer": "A",
        "analysis": ""
    },
    {
        "id": "202309081832117412",
        "title": "在我国战国时期，公孙龙提出“白马非马”。这个命题的错误在于它割裂了  ",
        "option": [
            "主要矛盾和次要矛盾的联系",
            "矛盾的主要方面和次要方面的联系",
            "矛盾的同一性和斗争性的联系",
            "矛盾的特殊性和普遍性的联系"
        ],
        "answer": "D",
        "analysis": ""
    },
    {
        "id": "20230908183262623",
        "title": "对待改革开放和社会主义现代化建设，有的人只看到存在的困难和问题，看不到取得的巨大成就；有的人只看到取得的巨大成就，看不到存在的困难和问题。这两种看问题的方法都是  ",
        "option": [
            "重点论",
            "均衡论",
            "一点论",
            "两点论"
        ],
        "answer": "C",
        "analysis": ""
    },
    {
        "id": "202309081832477873",
        "title": "“任何个别 无论怎样 都是一般”。这句话的正确含义是  ",
        "option": [
            "特殊性就是普遍性",
            "特殊性存在于普遍性之中",
            "普遍性是特殊性的总和",
            "特殊性中包含普遍性"
        ],
        "answer": "D",
        "analysis": ""
    },
    {
        "id": "202309081832300160",
        "title": "在唯物辩证法看来，水果同苹果、梨、香蕉、桔子等的关系是  ",
        "option": [
            "共性和个性的关系",
            "整体和部分的关系",
            "本质和现象的关系",
            "内容和形式的关系"
        ],
        "answer": "A",
        "analysis": ""
    },
    {
        "id": "202309081832378048",
        "title": "在马克思主义普遍原理指导下，从中国的基本国情出发，走自己的路。这体现了  ",
        "option": [
            "矛盾的同一性和斗争性的的统一",
            "矛盾的普遍性和特殊性的统一",
            "事物发展的量变和质变的统一",
            "事物发展的前进性和曲折性的统一"
        ],
        "answer": "B",
        "analysis": ""
    },
    {
        "id": "202309081832670842",
        "title": "“是就是是，不是就是不是，除此之外都是鬼话。”这是一种  ",
        "option": [
            "形而上学的观点",
            "相对主义的观点",
            "唯心主义的观点",
            "辩证法的观点"
        ],
        "answer": "A",
        "analysis": ""
    },
    {
        "id": "202309081832866067",
        "title": "真象和假象的区别在于  ",
        "option": [
            "真象是客观的，假象是主观的",
            "真象表现本质，假象不表现本质",
            "真象深藏于事物内部，假象外露于事物外部",
            "真象从正面直接地表现本质，假象从反面歪曲地表现本质"
        ],
        "answer": "D",
        "analysis": ""
    },
    {
        "id": "202309081832223067",
        "title": "有的哲学家说，在大风扬起的尘土中，每一粒尘土的运动状况都是纯粹必然的。这是一种",
        "option": [
            "辩证唯物主义决定论的观点",
            "形而上学的机械决定论的观点",
            "唯心主义非决定论的观点",
            "庸俗唯物主义的观点"
        ],
        "answer": "B",
        "analysis": ""
    },
    {
        "id": "202309081832360994",
        "title": "“或然率”是指  ",
        "option": [
            "可能性在质上的一种科学说明和测定",
            "可能性在量上的一种科学说明和测定",
            "必然性的一种科学说明和判定",
            "偶然性的一种科学说明和测定"
        ],
        "answer": "B",
        "analysis": ""
    },
    {
        "id": "202309081832491310",
        "title": "下列各项属于哲学基本问题内容的有  ",
        "option": [
            "思维与存在何者第一性",
            "思维能否掌握理论",
            "思维与存在是否有同一性",
            "思维能否正确地反映存在",
            "能否在我们关于现实世界的概念中正确地反映现实"
        ],
        "answer": "ACDE",
        "analysis": ""
    },
    {
        "id": "202309081832933320",
        "title": "以下各项属于主观唯心主义观点的有  ",
        "option": [
            "存在就是被感知",
            "物是观念的复合",
            "理在事先",
            "心外无事，心外无理",
            "吾心即宇宙"
        ],
        "answer": "ABDE",
        "analysis": ""
    },
    {
        "id": "202309081832938713",
        "title": "马克思主义哲学以前的唯物主义的缺陷有  ",
        "option": [
            "用机械力学的尺度去衡量物质的一切运动",
            "不能把世界理解为处于不断变化发展中的过程",
            "对社会历史的观点是唯心主义的",
            "不承认存在决定意识",
            "不承认社会存在决定社会意识"
        ],
        "answer": "ABCE",
        "analysis": ""
    },
    {
        "id": "202309081832648274",
        "title": "下列观点属于客观唯心主义的有  ",
        "option": [
            "事物是理念的影子",
            "“理在事先”",
            "世界是“绝对观念”的外化",
            "“未有天地万物，已有天地万物之理”",
            "现实的国家是国家观念的外化"
        ],
        "answer": "ABDCE",
        "analysis": ""
    },
    {
        "id": "202309081832425262",
        "title": "唯物主义形态的发展经历了  ",
        "option": [
            "古代朴素的唯物主义",
            "自然科学的唯物主义",
            "庸俗唯物主义",
            "近代形而上学唯物主义",
            "辩证唯物主义"
        ],
        "answer": "ADE",
        "analysis": ""
    },
    {
        "id": "202309081832715722",
        "title": "马克思主义哲学所讲的静止是指  ",
        "option": [
            "运动的一种特殊形式",
            "绝对不动",
            "排斥运动",
            "事物处于量变状态",
            "事物在特定参考系中未发生位置变动"
        ],
        "answer": "ADE",
        "analysis": ""
    },
    {
        "id": "202309081832418502",
        "title": "物质和运动的关系是  ",
        "option": [
            "运动是物质的固有属性",
            "物质是运动的承担者",
            "运动是物质的存在方式",
            "运动不一定是物质的运动",
            "物质不一定都在运动"
        ],
        "answer": "ABC",
        "analysis": ""
    },
    {
        "id": "202309081832157456",
        "title": "社会的物质性体现在  ",
        "option": [
            "劳动是社会产生和存在的决定性因素",
            "在社会中不存在精神的现象和活动",
            "物质资料的产生是社会历史的前提",
            "全部社会生活在本质上是实践的",
            "社会生活中不存在物质关系以外的其他关系"
        ],
        "answer": "ACD",
        "analysis": ""
    },
    {
        "id": "202309081832462548",
        "title": "意识的能动作用表现在  ",
        "option": [
            "反映客观世界",
            "创造物质世界",
            "通过实践改造客观世界",
            "创造理论体系",
            "为自然界创造秩序"
        ],
        "answer": "ACD",
        "analysis": ""
    },
    {
        "id": "202309081832337932",
        "title": "意识的本质是  ",
        "option": [
            "人脑的分泌物",
            "人脑的机能",
            "对物质世界的反映",
            "观念的系统",
            "人与生俱来的特性"
        ],
        "answer": "BC",
        "analysis": ""
    },
    {
        "id": "20230908183238760",
        "title": "物体的相对静止是  ",
        "option": [
            "物质分化的根本条件",
            "生命的根本条件",
            "物质存在与否的根本条件",
            "正确理解事物多样性的条件",
            "正确理解绝对运动的条件"
        ],
        "answer": "ABDE",
        "analysis": ""
    },
    {
        "id": "202309081832980229",
        "title": "客观规律性和主观能动性的关系是  ",
        "option": [
            "充分发挥主观能动性，才能认识和利用客观规律",
            "客观规律不能违背，所以限制了主观能动性的发挥",
            "正确发挥主观能动性，必须遵循客观规律",
            "越是强调尊重客观规律，就越能发挥主观能动性",
            "越是尊重客观规律，就越能发挥主观能动性"
        ],
        "answer": "ACDE",
        "analysis": ""
    },
    {
        "id": "202309081832723218",
        "title": "列宁的物质定义的理论意义在于  ",
        "option": [
            "坚持了唯物主义一元论",
            "反对了唯心主义和二元论",
            "坚持了唯物主义可知论",
            "克服了形而上学唯物主义物质观的缺陷",
            "为自然科学的发展提供了正确的世界观和方法论"
        ],
        "answer": "ABCDE",
        "analysis": ""
    },
    {
        "id": "202309081832879703",
        "title": "下列选项中，正确表述运动含义的有  ",
        "option": [
            "运动是新事物的产生和旧事物的灭亡",
            "运动是物质存在的方式",
            "运动是物质位置的移动",
            "运动是物质的根本属性",
            "运动指宇宙中发生的一切变化和过程"
        ],
        "answer": "BDE",
        "analysis": ""
    },
    {
        "id": "202309081832215705",
        "title": "下列选项中，正确表述运动和静止关系的有  ",
        "option": [
            "动者恒动，静者恒静",
            "运动是绝对的，静止是相对的",
            "动中有静，静中有动",
            "运动是有条件的，静止是无条件的",
            "无动则有静，无静则有动"
        ],
        "answer": "BC",
        "analysis": ""
    },
    {
        "id": "202309081832864445",
        "title": "下列说法中，表示时间一维性的有  ",
        "option": [
            "盛年不重来，一日难在晨",
            "失落黄金有分量，错过光阴无处寻",
            "光阴好比河中水，只能流去不复回",
            "莫说年纪小，人生容易老",
            "一寸光阴一寸金，寸金难买寸光阴"
        ],
        "answer": "ABCDE",
        "analysis": ""
    },
    {
        "id": "202309081832412385",
        "title": "下列成语和常用语中，正确说明意识能动性的有  ",
        "option": [
            "胸有成竹，料事如神",
            "纸上谈兵，画饼充饥",
            "天下无难事，只怕有心人",
            "不怕做不到，就怕想不到",
            "运筹帷幄之中，决胜千里之外"
        ],
        "answer": "ACE",
        "analysis": ""
    },
    {
        "id": "202309081832243187",
        "title": "尽管历史上罗马教廷把哥白尼的“日心说”当作异端邪说加以打击，毁掉哥白尼的数，监禁伽利略，但这既不能改变地球绕太阳转的规律，也不能阻止人们接收“日心说”。这一事实说明  ",
        "option": [
            "客观规律不以人的意志为转移",
            "人在客观规律面前无能为力",
            "客观规律起作用是无条件的",
            "真理中包含着不依赖于人的客观内容",
            "真理终究会战胜谬误"
        ],
        "answer": "ADE",
        "analysis": ""
    },
    {
        "id": "202309081832134945",
        "title": "自在自然与人化自然的分化与统一的基础是  ",
        "option": [
            "客体",
            "主体",
            "主体的实践",
            "人有意识有目的的改造客观世界的对象性活动",
            "意识"
        ],
        "answer": "CD",
        "analysis": ""
    },
    {
        "id": "20230908183226800",
        "title": "“观念的东西不外是移入人的头脑并在人的头脑中改造过的物质的东西而已，”这一命题揭示了  ",
        "option": [
            "观念的东西和物质的东西是对立的统一",
            "在意识中体现了主观和客观的统一",
            "人脑是意识的源泉",
            "观念的东西是对物质的东西的能动反映",
            "没有被反映者，就没有反映"
        ],
        "answer": "ABDE",
        "analysis": ""
    },
    {
        "id": "202309081832213094",
        "title": "劳动在人类社会发展中的地位和作用是  ",
        "option": [
            "劳动创造了人和人类社会",
            "劳动是一切历史的前提和基础",
            "劳动发展史是打开全部社会史的钥匙",
            "劳动是社会活动的全部内容",
            "劳动是人与自然之间的物质交换和能量变换过程"
        ],
        "answer": "ABCE",
        "analysis": ""
    },
    {
        "id": "202309081832590441",
        "title": "下列命题反映事物之间客观联系的有  ",
        "option": [
            "森林覆盖面的大小影响气候",
            "人口数量的多少影响社会发展",
            "客观条件的好坏影响人们行动的效果",
            "亚洲金融危机影响中国经济的增长速度",
            "天空出现彗星预示社会要爆发战争"
        ],
        "answer": "ABCD",
        "analysis": ""
    },
    {
        "id": "202309081832924494",
        "title": "判断一个事物是否是新事物的错误观点是  ",
        "option": [
            "根据它时间上出现的先后",
            "根据它的形式是否新奇",
            "根据它的力量是否强大",
            "是否符合事物发展的必然趋势",
            "是否具有强大的生命力和广阔的发展前途"
        ],
        "answer": "ABC",
        "analysis": ""
    },
    {
        "id": "202309081832156019",
        "title": "唯物辩证法与形而上学的对立表现在是否承认  ",
        "option": [
            "世界是物质的",
            "世界是可以认识的",
            "世界上的事物是普遍联系的",
            "世界上的事物是运动发展的",
            "矛盾是事物发展的根本原因"
        ],
        "answer": "CDE",
        "analysis": ""
    },
    {
        "id": "202309081832971450",
        "title": "下列各项正确反映量变与质变的辩证关系的有  ",
        "option": [
            "量变是质变的前提和必要准备",
            "质变是量变的前提和必要准备",
            "质变是量变的必然结果",
            "质变体现和巩固量变的成果，并为新的量变开拓道路",
            "事物的量变和质变相互转化过程体现了事物运动发展是连续性和非连续性的统一"
        ],
        "answer": "ACDE",
        "analysis": ""
    },
    {
        "id": "202309081832988274",
        "title": "“奢靡之始，危亡之渐。”包含的哲理有  ",
        "option": [
            "现象是本质的外部表现",
            "特殊性中包含着普遍性",
            "量变是质变的必要准备",
            "质变是量变的必然结果",
            "质变会引起新的量变"
        ],
        "answer": "CDE",
        "analysis": ""
    },
    {
        "id": "202309081832126045",
        "title": "割裂量变和质变的统一会导致  ",
        "option": [
            "庸俗唯物主义",
            "庸俗进化论",
            "改良主义",
            "激变论",
            "冒险主义"
        ],
        "answer": "BCDE",
        "analysis": ""
    },
    {
        "id": "202309081832339618",
        "title": "辩证法的否定观包含的内容有  ",
        "option": [
            "辩证的否定是自我否定",
            "辩证的否定是联系的环节",
            "辩证的否定是发展的环节",
            "辩证的否定是扬弃",
            "辩证的否定是连续性和非连续性的统一"
        ],
        "answer": "ABCDE",
        "analysis": ""
    },
    {
        "id": "202309081832783327",
        "title": "辩证的否定具有两个重要特点，分别是  ",
        "option": [
            "否定是联系的环节",
            "否定是发展的环节",
            "否定与肯定绝对对立",
            "否定是由外力推动的",
            "否定中不包含肯定"
        ],
        "answer": "AB",
        "analysis": ""
    },
    {
        "id": "202309081832547825",
        "title": "否定之否定规律揭示了事物的发展  ",
        "option": [
            "是自我发展、自我完善的过程",
            "是回到原来出发点的循环过程",
            "是直线式前进的过程",
            "是前进性和曲折性相统一的过程",
            "量变和质变相统一的过程"
        ],
        "answer": "AD",
        "analysis": ""
    },
    {
        "id": "202309081832508696",
        "title": "同一性是矛盾的基本属性。下列命题中属于矛盾的同一性含义的有  ",
        "option": [
            "矛盾双方相互排斥",
            "矛盾双方相互依存",
            "矛盾双方相互贯通",
            "矛盾双方相互渗透",
            "矛盾双方相互转化"
        ],
        "answer": "BCDE",
        "analysis": ""
    },
    {
        "id": "202309081832915904",
        "title": "包含矛盾双方相互依存、相互转化辩证法思想的有  ",
        "option": [
            "祸兮福所倚，福兮祸所伏",
            "月晕而风，础润而雨",
            "千里之堤，溃于蚁穴",
            "物极必反，相反相成",
            "乐极生悲，苦尽甘来"
        ],
        "answer": "ADE",
        "analysis": ""
    },
    {
        "id": "202309081832697738",
        "title": "矛盾的同一性在事物发展中的作用表现在  ",
        "option": [
            "使事物保持相对稳定，为事物的存在和发展提供必要的前提",
            "矛盾双方互相从对方吸取有利于自身的因素而得到发展",
            "规定了事物向对立面转化的基本趋势",
            "推动矛盾双方的力量对比和相互关系发生变化",
            "突破事物存在的限度，实现事物的质变"
        ],
        "answer": "ABC",
        "analysis": ""
    },
    {
        "id": "202309081832208838",
        "title": "下列表述，能体现重视矛盾特殊性的有  ",
        "option": [
            "对症下药，量体裁衣",
            "欲擒故纵，声东击西",
            "因时制宜，因地制宜",
            "物极必反，相反相成",
            "因材施教，因人而异"
        ],
        "answer": "ACE",
        "analysis": ""
    },
    {
        "id": "202309081832189683",
        "title": "矛盾发展的不平衡性是指  ",
        "option": [
            "内部矛盾与外部矛盾的不平衡",
            "主要矛盾与次要矛盾的不平衡",
            "普遍矛盾与特殊矛盾的不平衡",
            "矛盾的主要方面与次要方面的不平衡",
            "形式逻辑矛盾与辩证矛盾的不平衡"
        ],
        "answer": "BD",
        "analysis": ""
    },
    {
        "id": "202309081832914908",
        "title": "看问题、办事情都要坚持  ",
        "option": [
            "两点论和重点论的统一",
            "两点论和均衡论的统一",
            "一点论和重点论的统-",
            "一点论和均衡论的统一",
            "既要全面，又要抓重点"
        ],
        "answer": "AE",
        "analysis": ""
    },
    {
        "id": "202309081832619492",
        "title": "对立统一规律是唯物辩证法的实质和核心，这是因为  ",
        "option": [
            "对立统一规律揭示了普遍联系的根本内容",
            "对立统一规律揭示了变化发展的内在动力",
            "对立统一规律是贯穿于辩证法其它规律和范畴的中心线索",
            "矛盾分析法是最根本的认识方法",
            "是否承认矛盾是事物发展的动力，是辩证法和形而上学的根本分歧"
        ],
        "answer": "ABCDE",
        "analysis": ""
    },
    {
        "id": "202309081832880705",
        "title": "正确处理部分与整体的关系，就要做到  ",
        "option": [
            "着眼于整体，要求局部服从整体",
            "以局部利益损害整体利益",
            "承认局部的相对独立性和特定的重要作用",
            "片面强调整体利益抹煞局部利益",
            "把整体利益与局部利益结合起来"
        ],
        "answer": "ACE",
        "analysis": ""
    },
    {
        "id": "202309081832320554",
        "title": "下列属于因果联系的有  ",
        "option": [
            "摩擦生热，热胀冷缩",
            "冬去春来，夏尽秋至",
            "电闪雷鸣，风雨来至",
            "勤学出智慧，实践出真知",
            "虚心使人进步，骄傲使人落后"
        ],
        "answer": "ADE",
        "analysis": ""
    },
    {
        "id": "202309081832886788",
        "title": "内容和形式的相互作用是  ",
        "option": [
            "内容决定形式",
            "形式决定内容",
            "形式对内容有重大的反作用",
            "当形式与内容适合时，对内容的发展起积极促进作用",
            "当形式与内容不适合时，对内容的发展起消极的阻碍作用",
            "CDE"
        ],
        "answer": "ACDE",
        "analysis": ""
    }
]